{
    "model_type": "MLP Classifier (Multi-Label)",
    "training_date": "2025-11-19 11:19:33",
    "data_sources": {
        "normal": "data/processed/1118_features_cleaned.csv",
        "fluctuating": "data/processed/1118_features_fluctuating_cleaned.csv",
        "misalignment": "data/processed/1118_features_misalignment_cleaned.csv"
    },
    "label_mapping": {
        "fluctuating": [
            1,
            0
        ],
        "misalignment": [
            0,
            1
        ],
        "normal": [
            0,
            0
        ]
    },
    "dataset": {
        "total_samples": 2124,
        "train_samples": 1805,
        "test_samples": 319,
        "feature_dim": 77,
        "label_distribution": {
            "Fluctuating": 719,
            "Misalignment": 702,
            "Normal": 703
        }
    },
    "architecture": {
        "input_size": 77,
        "hidden_layers": [
            64,
            32
        ],
        "output_size": 2,
        "total_parameters": 7138
    },
    "hyperparameters": {
        "epochs": 20,
        "batch_size": 32,
        "learning_rate": 0.001,
        "optimizer": "Adam",
        "loss_function": "BCELoss",
        "random_seed": 42
    },
    "training_results": {
        "training_time_seconds": 1.824822,
        "final_loss": 0.00022643793342643206,
        "min_loss": 0.00022643793342643206,
        "loss_history": [
            0.5217808845796084,
            0.13473356404063994,
            0.034261450563606466,
            0.013521468993929918,
            0.006930326663055702,
            0.003929376529668572,
            0.002659575799234996,
            0.0019178736348342347,
            0.0014229670885374378,
            0.001120219528705715,
            0.0008952278219288003,
            0.0007303389940173937,
            0.0006225497531806724,
            0.0005113469151342942,
            0.00043626673128496725,
            0.00037639954315269727,
            0.0003264470922563066,
            0.0002854172637358843,
            0.00025373407397797054,
            0.00022643793342643206
        ]
    },
    "saved_files": {
        "model": "models\\mlp_classifier.pth",
        "torchscript": "models\\mlp_classifier.pt",
        "scaler": "models\\scaler_mlp.pkl",
        "data_split": "models\\data_split.npz",
        "loss_curve": "results/mlp\\mlp_loss_curve.png"
    }
}